bootstrap4c4d/__init__.py
bootstrap4c4d/__main__.py
bootstrap4c4d/cli.py
bootstrap4c4d/io.py
bootstrap4c4d/classes/__init__.py
bootstrap4c4d/classes/description.py
bootstrap4c4d/classes/fp.py
bootstrap4c4d/classes/template.py
bootstrap4c4d/reducers/__init__.py
bootstrap4c4d/reducers/h.py
bootstrap4c4d/reducers/res.py
bootstrap4c4d/reducers/str.py
bootstrap4c4d/render/__init__.py
bootstrap4c4d/render/h.py
bootstrap4c4d/render/res.py
bootstrap4c4d/render/str.py
bootstrap4c4d/utilities/__init__.py
bootstrap4c4d/utilities/cli.py
bootstrap4c4d/utilities/path.py
bootstrap4c4d_beesperester-2.1.0.dist-info/LICENSE
bootstrap4c4d_beesperester-2.1.0.dist-info/METADATA
bootstrap4c4d_beesperester-2.1.0.dist-info/WHEEL
bootstrap4c4d_beesperester-2.1.0.dist-info/top_level.txt
bootstrap4c4d_beesperester-2.1.0.dist-info/RECORD
