Metadata-Version: 2.1
Name: bootstrap4c4d-beesperester
Version: 2.1.0
Summary: Jumpstart Cinema 4D plugin development
Home-page: https://github.com/beesperester/cinema4d-bootstrap
Author: Bernhard Esperester
Author-email: bernhard@esperester.de
License: UNKNOWN
Platform: UNKNOWN
Classifier: Programming Language :: Python :: 3
Classifier: License :: OSI Approved :: MIT License
Classifier: Operating System :: OS Independent
Requires-Python: >=3.6
